README.md
setup.py
mudrex/__init__.py
mudrex/about.py
mudrex/webhook.py
mudrex.egg-info/PKG-INFO
mudrex.egg-info/SOURCES.txt
mudrex.egg-info/dependency_links.txt
mudrex.egg-info/requires.txt
mudrex.egg-info/top_level.txt
mudrex.egg-info/zip-safe