Metadata-Version: 2.1
Name: mudrex
Version: 0.1.2
Summary: Send external webhook signals to Mudrex platform.
Home-page: https://github.com/surajiyer/mudrex
Author: Suraj Iyer
Author-email: me@surajiyer.com
License: MIT
Platform: UNKNOWN
